distyll/__init__.py
distyll/config.py
distyll/db.py
distyll/llm/__init__.py
distyll/llm/utils.py
distyll/loggerconfig.py
distyll/text/__init__.py
distyll/text/text.py
distyll/transcripts/__init__.py
distyll/transcripts/transcripts.py
distyll/utils.py
distyll_info-0.3.2.dist-info/METADATA
distyll_info-0.3.2.dist-info/WHEEL
distyll_info-0.3.2.dist-info/RECORD
