Metadata-Version: 2.1
Name: distyll-info
Version: 0.3.2
Summary: Information parsing assistant
License: MIT
Author: JP Hwang
Author-email: 61258750+databyjp@users.noreply.github.com
Requires-Python: >=3.10,<4.0
Classifier: License :: OSI Approved :: MIT License
Classifier: Programming Language :: Python :: 3
Classifier: Programming Language :: Python :: 3.10
Classifier: Programming Language :: Python :: 3.11
Classifier: Programming Language :: Python :: 3.12
Requires-Dist: beautifulsoup4 (>=4.13.4,<5.0.0)
Requires-Dist: jupyter (>=1.1.1,<2.0.0)
Requires-Dist: moviepy (>=1.0.3,<2.0.0)
Requires-Dist: openai (>=1.82.0,<2.0.0)
Requires-Dist: pydub (>=0.25.1,<0.26.0)
Requires-Dist: pypdf (>=4.3.1,<5.0.0)
Requires-Dist: weaviate-client (>=4.14.4,<5.0.0)
Requires-Dist: yt-dlp (>=2023.12.30,<2024.0.0)
